sgn_inspect/__init__.py
sgn_inspect/_version.py
sgn_inspect/cli.py
sgn_inspect/registry.py
sgn_inspect/tests/__init__.py
sgn_inspect/tests/test_cli.py
sgn_inspect/tests/test_registry.py
sgn_inspect-0.1.0.dist-info/METADATA
sgn_inspect-0.1.0.dist-info/WHEEL
sgn_inspect-0.1.0.dist-info/entry_points.txt
sgn_inspect-0.1.0.dist-info/licenses/LICENSE
sgn_inspect-0.1.0.dist-info/RECORD
